fuzzbucket_client/__init__.py
fuzzbucket_client/__main__.py
fuzzbucket_client/__version__.py
fuzzbucket_client/datetime_ext.py
fuzzbucket_client-0.15.0.dist-info/METADATA
fuzzbucket_client-0.15.0.dist-info/WHEEL
fuzzbucket_client-0.15.0.dist-info/entry_points.txt
fuzzbucket_client-0.15.0.dist-info/licenses/LICENSE.md
fuzzbucket_client-0.15.0.dist-info/RECORD
