Metadata-Version: 2.3
Name: fuzzbucket-client
Version: 0.15.0
Summary: Command line client for fuzzbucket
Project-URL: Homepage, https://github.com/rstudio/fuzzbucket
Author-email: Posit Humans <ptd-dev+fuzzbucket@posit.co>
License-Expression: MIT
License-File: LICENSE.md
Requires-Python: <4,>=3.9
